cythonrgbasearch/README.MD
cythonrgbasearch/__init__.py
cythonrgbasearch/requirements.txt
cythonrgbasearch/thirdparty.json
cythonrgbasearch-0.10.dist-info/LICENSE.rst
cythonrgbasearch-0.10.dist-info/METADATA
cythonrgbasearch-0.10.dist-info/WHEEL
cythonrgbasearch-0.10.dist-info/top_level.txt
cythonrgbasearch-0.10.dist-info/RECORD
